{"State.22545118-8cf3-4679-afc6-1b28a6c72786": {"id": "22545118-8cf3-4679-afc6-1b28a6c72786", "created_at": "2023-09-20T18:16:48.466626", "updated_at": "2023-09-20T18:16:48.466775", "name": "California", "__class__": "State"}, "State.53fd7fdd-4194-4eb8-a8a5-0bcd8d6c54fc": {"id": "53fd7fdd-4194-4eb8-a8a5-0bcd8d6c54fc", "created_at": "2023-09-20T18:16:48.467160", "updated_at": "2023-09-20T18:16:48.467179", "name": "Arizona", "__class__": "State"}, "Place.e329e425-b86c-47c1-96cc-ea03f8f1d081": {"id": "e329e425-b86c-47c1-96cc-ea03f8f1d081", "created_at": "2023-09-20T18:16:48.467639", "updated_at": "2023-09-20T18:16:48.467725", "city_id": "0001", "user_id": "0001", "name": "My little house", "number_rooms": 4, "number_bathrooms": 2, "max_guest": 10, "price_by_night": 300, "latitude": 37.773972, "longitude": -122.431297, "__class__": "Place"}}